lims2/__init__.py
lims2/_version.py
lims2/chart.py
lims2/client.py
lims2/config.py
lims2/exceptions.py
lims2/network.py
lims2/oss_base.py
lims2/progress.py
lims2/storage.py
lims2/thumbnail.py
lims2/utils.py
lims2_cli/__init__.py
lims2_cli/main.py
lims2_sdk-0.7.8.dist-info/METADATA
lims2_sdk-0.7.8.dist-info/WHEEL
lims2_sdk-0.7.8.dist-info/entry_points.txt
lims2_sdk-0.7.8.dist-info/top_level.txt
lims2_sdk-0.7.8.dist-info/RECORD
