Metadata-Version: 2.4
Name: lims2-sdk
Version: 0.7.8
Summary: 生信云平台 Python SDK，提供图表上传和文件存储功能
Author-email: Lims2 Team <support@lims2.com>
License: MIT
Requires-Python: >=3.9
Requires-Dist: requests>=2.25.0
Requires-Dist: click>=8.0.0
Requires-Dist: oss2>=2.15.0
Requires-Dist: orjson>=3.8.0
Requires-Dist: tenacity>=8.0.0
Requires-Dist: plotly==6.2.0
Requires-Dist: kaleido==0.2.1
